idotmatrix_sdk/__init__.py
idotmatrix_sdk/idotmatrix.py
idotmatrix_sdk/idotmatrix_base.py
idotmatrix_sdk/idotmatrix_color.py
idotmatrix_sdk/idotmatrix_countdown.py
idotmatrix_sdk/idotmatrix_effects.py
idotmatrix_sdk/idotmatrix_image.py
idotmatrix_sdk/idotmatrix_screen.py
idotmatrix_sdk/idotmatrix_time.py
idotmatrix_sdk-0.1.dist-info/METADATA
idotmatrix_sdk-0.1.dist-info/WHEEL
idotmatrix_sdk-0.1.dist-info/RECORD
