Metadata-Version: 2.4
Name: idotmatrix-sdk
Version: 0.1
Summary: Allow connect with I Dot Matrix screens
Author-email: Miguel Ángel López <miguel.angel.lopez.vicente@gmail.com>
License-Expression: MIT
Requires-Python: >3.9
Requires-Dist: bleak>=0.22.3
